[
  {
    "id": 5691898,
    "slug": "oh2lmy",
    "title": "Hello World",
    "book_id": 881860,
    "book": {
      "id": 881860,
      "type": "Book",
      "slug": "hexo",
      "name": "hexo博客文章",
      "user_id": 1175890,
      "description": "个人博客文章",
      "creator_id": 1175890,
      "public": 1,
      "items_count": 1,
      "likes_count": 0,
      "watches_count": 1,
      "content_updated_at": "2020-04-03T09:28:05.854Z",
      "updated_at": "2020-04-03T09:28:05.000Z",
      "created_at": "2020-03-24T00:30:25.000Z",
      "namespace": "linhk1606/hexo",
      "user": {
        "id": 1175890,
        "type": "User",
        "login": "linhk1606",
        "name": "Linhk1606",
        "description": "OIer",
        "avatar_url": "https://cdn.nlark.com/yuque/0/2020/png/1175890/1585272853621-avatar/04f8c3f7-a562-455a-b8c3-a4fdaa547e26.png",
        "books_count": 1,
        "public_books_count": 1,
        "followers_count": 0,
        "following_count": 1,
        "created_at": "2020-03-23T09:14:13.000Z",
        "updated_at": "2020-03-29T14:55:46.000Z",
        "_serializer": "v2.user"
      },
      "_serializer": "v2.book"
    },
    "user_id": 1175890,
    "creator": {
      "id": 1175890,
      "type": "User",
      "login": "linhk1606",
      "name": "Linhk1606",
      "description": "OIer",
      "avatar_url": "https://cdn.nlark.com/yuque/0/2020/png/1175890/1585272853621-avatar/04f8c3f7-a562-455a-b8c3-a4fdaa547e26.png",
      "books_count": 1,
      "public_books_count": 1,
      "followers_count": 0,
      "following_count": 1,
      "created_at": "2020-03-23T09:14:13.000Z",
      "updated_at": "2020-03-29T14:55:46.000Z",
      "_serializer": "v2.user"
    },
    "format": "lake",
    "body": "\n<br />date: \"2020-3-30 00:00:00\"<br />body: [article, comments]<br />cover: false<br />valine:<br /> placeholder: 有什么感想? 发射犇犇<br />mathjax: true<br />tags:<br />- test<br />categories:<br />- [Dev, hexo]<br />\n<br />---\n> 这篇文章来自于云端的语雀\n\n<!--more-->\n<a name=\"trTVW\"></a>\n## 语雀云端编辑Hexo文章\n> 让你的 [Hexo](https://hexo.io) 静态博客实现与 [Wordpress](https://wordpress.org) 一样丝滑的文章发布体验\n> 参见 https://zhwei.cn/hexo-github-actions-yuque/ \n<br />\n\n<a name=\"nFaOR\"></a>\n## 复杂格式测试\n<a name=\"ih913\"></a>\n#### Container\n\n- 结果: <red>测试失败</red> , 腾讯云函数无法激活GitHub Actions\n<a name=\"MKVQi\"></a>\n#### Code Block\n\n\n```cpp\n#include <cstdio>\n\nint main()\n{\n    puts(\"U AK IOI!\");\n    return main();\n}\n```\n\n- 结果: <green>测试成功</green><br />\n\n\n\n<a name=\"zXYnB\"></a>\n#### 折叠框\n\n- 结果: <red>测试失败</red> , 腾讯云函数无法激活GitHub Actions\n",
    "body_draft": "\n<br />date: \"2020-3-30 00:00:00\"<br />body: [article, comments]<br />cover: false<br />valine:<br /> placeholder: 有什么感想? 发射犇犇<br />mathjax: true<br />tags:<br />- test<br />categories:<br />- [Dev, hexo]<br />\n<br />---\n> 这篇文章来自于云端的语雀\n\n<!--more-->\n<a name=\"trTVW\"></a>\n## 语雀云端编辑Hexo文章\n> 让你的 [Hexo](https://hexo.io) 静态博客实现与 [Wordpress](https://wordpress.org) 一样丝滑的文章发布体验\n> 参见 https://zhwei.cn/hexo-github-actions-yuque/ \n<br />\n\n<a name=\"nFaOR\"></a>\n## 复杂格式测试\n<a name=\"ih913\"></a>\n#### Container\n\n- 结果: <red>测试失败</red> , 腾讯云函数无法激活GitHub Actions\n<a name=\"MKVQi\"></a>\n#### Code Block\n\n\n```cpp\n#include <cstdio>\n\nint main()\n{\n    puts(\"U AK IOI!\");\n    return main();\n}\n```\n\n- 结果: <green>测试成功</green><br />\n\n\n\n<a name=\"zXYnB\"></a>\n#### 折叠框\n\n- 结果: <red>测试失败</red> , 腾讯云函数无法激活GitHub Actions\n",
    "body_html": "<!doctype html><div class=\"lake-content-editor-core lake-engine lake-typography-classic\" data-lake-element=\"root\"><p data-lake-id=\"f65514329048c34b89eac82f1e24f85b\" style=\"font-size: 14px; color: rgb(38, 38, 38); line-height: 1.74; letter-spacing: 0.05em; outline-style: none; overflow-wrap: break-word; margin: 0px;\"><br></p><p data-lake-id=\"116ddff8e632eba8724aac7994875690\" style=\"font-size: 14px; color: rgb(38, 38, 38); line-height: 1.74; letter-spacing: 0.05em; outline-style: none; overflow-wrap: break-word; margin: 0px;\">date: \"2020-3-30 00:00:00\"</p><p data-lake-id=\"f0b7e771763a9bb17f9655cd1b8f4cda\" style=\"font-size: 14px; color: rgb(38, 38, 38); line-height: 1.74; letter-spacing: 0.05em; outline-style: none; overflow-wrap: break-word; margin: 0px;\">body: [article, comments]</p><p data-lake-id=\"37e8cbef3d702a9a483aebcd0bd7a27d\" style=\"font-size: 14px; color: rgb(38, 38, 38); line-height: 1.74; letter-spacing: 0.05em; outline-style: none; overflow-wrap: break-word; margin: 0px;\">cover: false</p><p data-lake-id=\"9a4fdff11b4fa5d67f7f154b18a6b72f\" style=\"font-size: 14px; color: rgb(38, 38, 38); line-height: 1.74; letter-spacing: 0.05em; outline-style: none; overflow-wrap: break-word; margin: 0px;\">valine:</p><p data-lake-id=\"1f4a705485a45919fc0925aef6cdb697\" style=\"font-size: 14px; color: rgb(38, 38, 38); line-height: 1.74; letter-spacing: 0.05em; outline-style: none; overflow-wrap: break-word; margin: 0px;\">&nbsp;placeholder: 有什么感想? 发射犇犇</p><p data-lake-id=\"0564e95a046d27843f61ac9099628e4f\" style=\"font-size: 14px; color: rgb(38, 38, 38); line-height: 1.74; letter-spacing: 0.05em; outline-style: none; overflow-wrap: break-word; margin: 0px;\">mathjax: true</p><p data-lake-id=\"09841c28b00c7a7d569b52cb59f76cbe\" style=\"font-size: 14px; color: rgb(38, 38, 38); line-height: 1.74; letter-spacing: 0.05em; outline-style: none; overflow-wrap: break-word; margin: 0px;\">tags:</p><p data-lake-id=\"95d5ba826c80dd2339c6bfe124282e66\" style=\"font-size: 14px; color: rgb(38, 38, 38); line-height: 1.74; letter-spacing: 0.05em; outline-style: none; overflow-wrap: break-word; margin: 0px;\">- test</p><p data-lake-id=\"95243f401ea3360e90aea7111da99935\" style=\"font-size: 14px; color: rgb(38, 38, 38); line-height: 1.74; letter-spacing: 0.05em; outline-style: none; overflow-wrap: break-word; margin: 0px;\">categories:</p><p data-lake-id=\"ec627cd9ba6f4469b174cb983be99320\" style=\"font-size: 14px; color: rgb(38, 38, 38); line-height: 1.74; letter-spacing: 0.05em; outline-style: none; overflow-wrap: break-word; margin: 0px;\">- [Dev, hexo]</p><p data-lake-id=\"df44182a667e6aeec7cf972d37754739\" style=\"font-size: 14px; color: rgb(38, 38, 38); line-height: 1.74; letter-spacing: 0.05em; outline-style: none; overflow-wrap: break-word; margin: 0px;\"><br></p><p data-lake-id=\"d0f25603b0b8a1f76e91065a38b40407\" style=\"font-size: 14px; color: rgb(38, 38, 38); line-height: 1.74; letter-spacing: 0.05em; outline-style: none; overflow-wrap: break-word; margin: 0px;\"><span style=\"color: #6A737D;\">---</span></p><blockquote style=\"margin-top: 5px; margin-bottom: 5px; padding-left: 1em; margin-left: 0px; border-left: 3px solid rgb(238, 238, 238); opacity: 0.6;\"><p data-lake-id=\"90254a0cf09df4e794183f3fd8f8bc8d\" style=\"font-size: 14px; color: rgb(38, 38, 38); line-height: 1.74; letter-spacing: 0.05em; outline-style: none; overflow-wrap: break-word; margin: 0px;\">这篇文章来自于云端的语雀</p></blockquote><p data-lake-id=\"1614ef987dbe837b7a28bc67218ad48a\" style=\"font-size: 14px; color: rgb(38, 38, 38); line-height: 1.74; letter-spacing: 0.05em; outline-style: none; overflow-wrap: break-word; margin: 0px;\">&lt;!--more--&gt;</p><h2 data-lake-id=\"333084cbba87814bcde072999a188966\" id=\"trTVW\" style=\"padding: 7px 0px; margin: 0px; font-weight: 700; font-size: 24px; line-height: 32px;\">语雀云端编辑Hexo文章</h2><blockquote style=\"margin-top: 5px; margin-bottom: 5px; padding-left: 1em; margin-left: 0px; border-left: 3px solid rgb(238, 238, 238); opacity: 0.6;\"><p data-lake-id=\"76092aee7111b8b9f517aa005642ba69\" style=\"font-size: 14px; color: rgb(38, 38, 38); line-height: 1.74; letter-spacing: 0.05em; outline-style: none; overflow-wrap: break-word; margin: 0px;\">让你的&nbsp;<a href=\"https://hexo.io\" target=\"_blank\">Hexo</a>&nbsp;静态博客实现与 <a href=\"https://wordpress.org\" target=\"_blank\">Wordpress</a>&nbsp;一样丝滑的文章发布体验</p><p data-lake-id=\"330288d10127f7cdbec9e0004f2853bf\" style=\"font-size: 14px; color: rgb(38, 38, 38); line-height: 1.74; letter-spacing: 0.05em; outline-style: none; overflow-wrap: break-word; margin: 0px;\">参见 https://zhwei.cn/hexo-github-actions-yuque/&nbsp;\n<br></p></blockquote><h2 data-lake-id=\"b6ad50776958d4df6750a5a02ff64a89\" id=\"nFaOR\" style=\"padding: 7px 0px; margin: 0px; font-weight: 700; font-size: 24px; line-height: 32px;\">复杂格式测试</h2><h4 data-lake-id=\"0b3e57f310b7c059be9c73c5fa0cbda8\" id=\"ih913\" style=\"padding: 7px 0px; margin: 0px; font-weight: 700; font-size: 16px; line-height: 24px;\">Container</h4><ul data-lake-id=\"6e16d3cebe901eae886c0c2976dbb6e1\" lake-indent=\"0\" style=\"list-style-type: disc; margin: 0px; padding-left: 23px; font-size: 14px; color: rgb(38, 38, 38); line-height: 1.74; letter-spacing: 0.05em; outline-style: none; overflow-wrap: break-word;\"><li data-lake-id=\"814a6732be5815f744ca2e3eec86ac78\">结果: &lt;red&gt;测试失败&lt;/red&gt; , 腾讯云函数无法激活GitHub Actions</li></ul><h4 data-lake-id=\"3efde790e31791d18cd181be40b10be1\" id=\"MKVQi\" style=\"padding: 7px 0px; margin: 0px; font-weight: 700; font-size: 16px; line-height: 24px;\">Code Block</h4><p data-lake-id=\"16344c0ab8d8c2b3a6970ea796962918\" style=\"font-size: 14px; color: rgb(38, 38, 38); line-height: 1.74; letter-spacing: 0.05em; outline-style: none; overflow-wrap: break-word; margin: 0px;\"><br></p><div data-card-type=\"block\" data-lake-card=\"codeblock\" id=\"2GlFT\" class=\"\"><div class=\"lake-codeblock-content\" style=\"border: 1px solid rgb(232, 232, 232); max-width: 750px; color: rgb(89, 89, 89); margin: 0px; padding: 0px; background: rgb(249, 249, 249);\"><div class=\"\" style=\"color: rgb(89, 89, 89); margin: 0px; padding: 16px; background: none 0% 0% / auto repeat scroll padding-box border-box rgba(0, 0, 0, 0);\"><pre class=\"cm-s-default\" style=\"color: rgb(89, 89, 89); margin: 0px; padding: 0px; background: none 0% 0% / auto repeat scroll padding-box border-box rgba(0, 0, 0, 0);\"><span class=\"lake-preview-line\" style=\"color: rgb(89, 89, 89); margin: 0px; padding: 0px; background: none 0% 0% / auto repeat scroll padding-box border-box rgba(0, 0, 0, 0);\"><span class=\"lake-preview-line-number lake-lm-pad-level-0\" style=\"color: rgb(191, 191, 191); margin: 0px 8px 0px 0px; padding: 0px; background: none 0% 0% / auto repeat scroll padding-box border-box rgba(0, 0, 0, 0);\"></span><span class=\"lake-preview-codeblock-content\" style=\"color: rgb(89, 89, 89); margin: 0px; padding: 0px; background: none 0% 0% / auto repeat scroll padding-box border-box rgba(0, 0, 0, 0);\"><span class=\"cm-meta\" style=\"color: rgb(31, 127, 154); margin: 0px; padding: 0px; background: none 0% 0% / auto repeat scroll padding-box border-box rgba(0, 0, 0, 0);\">#include &lt;cstdio&gt;</span>\n</span></span><span class=\"lake-preview-line\" style=\"color: rgb(89, 89, 89); margin: 0px; padding: 0px; background: none 0% 0% / auto repeat scroll padding-box border-box rgba(0, 0, 0, 0);\"><span class=\"lake-preview-line-number lake-lm-pad-level-0\" style=\"color: rgb(191, 191, 191); margin: 0px 8px 0px 0px; padding: 0px; background: none 0% 0% / auto repeat scroll padding-box border-box rgba(0, 0, 0, 0);\"></span><span class=\"lake-preview-codeblock-content\" style=\"color: rgb(89, 89, 89); margin: 0px; padding: 0px; background: none 0% 0% / auto repeat scroll padding-box border-box rgba(0, 0, 0, 0);\">\n</span></span><span class=\"lake-preview-line\" style=\"color: rgb(89, 89, 89); margin: 0px; padding: 0px; background: none 0% 0% / auto repeat scroll padding-box border-box rgba(0, 0, 0, 0);\"><span class=\"lake-preview-line-number lake-lm-pad-level-0\" style=\"color: rgb(191, 191, 191); margin: 0px 8px 0px 0px; padding: 0px; background: none 0% 0% / auto repeat scroll padding-box border-box rgba(0, 0, 0, 0);\"></span><span class=\"lake-preview-codeblock-content\" style=\"color: rgb(89, 89, 89); margin: 0px; padding: 0px; background: none 0% 0% / auto repeat scroll padding-box border-box rgba(0, 0, 0, 0);\"><span class=\"cm-type\" style=\"color: rgb(34, 134, 58); margin: 0px; padding: 0px; background: none 0% 0% / auto repeat scroll padding-box border-box rgba(0, 0, 0, 0);\">int</span> <span class=\"cm-def\" style=\"color: rgb(0, 92, 197); margin: 0px; padding: 0px; background: none 0% 0% / auto repeat scroll padding-box border-box rgba(0, 0, 0, 0);\">main</span>()\n</span></span><span class=\"lake-preview-line\" style=\"color: rgb(89, 89, 89); margin: 0px; padding: 0px; background: none 0% 0% / auto repeat scroll padding-box border-box rgba(0, 0, 0, 0);\"><span class=\"lake-preview-line-number lake-lm-pad-level-0\" style=\"color: rgb(191, 191, 191); margin: 0px 8px 0px 0px; padding: 0px; background: none 0% 0% / auto repeat scroll padding-box border-box rgba(0, 0, 0, 0);\"></span><span class=\"lake-preview-codeblock-content\" style=\"color: rgb(89, 89, 89); margin: 0px; padding: 0px; background: none 0% 0% / auto repeat scroll padding-box border-box rgba(0, 0, 0, 0);\">{\n</span></span><span class=\"lake-preview-line\" style=\"color: rgb(89, 89, 89); margin: 0px; padding: 0px; background: none 0% 0% / auto repeat scroll padding-box border-box rgba(0, 0, 0, 0);\"><span class=\"lake-preview-line-number lake-lm-pad-level-0\" style=\"color: rgb(191, 191, 191); margin: 0px 8px 0px 0px; padding: 0px; background: none 0% 0% / auto repeat scroll padding-box border-box rgba(0, 0, 0, 0);\"></span><span class=\"lake-preview-codeblock-content\" style=\"color: rgb(89, 89, 89); margin: 0px; padding: 0px; background: none 0% 0% / auto repeat scroll padding-box border-box rgba(0, 0, 0, 0);\">    <span class=\"cm-variable\" style=\"color: rgb(89, 89, 89); margin: 0px; padding: 0px; background: none 0% 0% / auto repeat scroll padding-box border-box rgba(0, 0, 0, 0);\">puts</span>(<span class=\"cm-string\" style=\"color: rgb(102, 153, 0); margin: 0px; padding: 0px; background: none 0% 0% / auto repeat scroll padding-box border-box rgba(0, 0, 0, 0);\">\"U AK IOI!\"</span>);\n</span></span><span class=\"lake-preview-line\" style=\"color: rgb(89, 89, 89); margin: 0px; padding: 0px; background: none 0% 0% / auto repeat scroll padding-box border-box rgba(0, 0, 0, 0);\"><span class=\"lake-preview-line-number lake-lm-pad-level-0\" style=\"color: rgb(191, 191, 191); margin: 0px 8px 0px 0px; padding: 0px; background: none 0% 0% / auto repeat scroll padding-box border-box rgba(0, 0, 0, 0);\"></span><span class=\"lake-preview-codeblock-content\" style=\"color: rgb(89, 89, 89); margin: 0px; padding: 0px; background: none 0% 0% / auto repeat scroll padding-box border-box rgba(0, 0, 0, 0);\">    <span class=\"cm-keyword\" style=\"color: rgb(215, 58, 73); margin: 0px; padding: 0px; background: none 0% 0% / auto repeat scroll padding-box border-box rgba(0, 0, 0, 0);\">return</span> <span class=\"cm-variable\" style=\"color: rgb(89, 89, 89); margin: 0px; padding: 0px; background: none 0% 0% / auto repeat scroll padding-box border-box rgba(0, 0, 0, 0);\">main</span>();\n</span></span><span class=\"lake-preview-line\" style=\"color: rgb(89, 89, 89); margin: 0px; padding: 0px; background: none 0% 0% / auto repeat scroll padding-box border-box rgba(0, 0, 0, 0);\"><span class=\"lake-preview-line-number lake-lm-pad-level-0\" style=\"color: rgb(191, 191, 191); margin: 0px 8px 0px 0px; padding: 0px; background: none 0% 0% / auto repeat scroll padding-box border-box rgba(0, 0, 0, 0);\"></span><span class=\"lake-preview-codeblock-content\" style=\"color: rgb(89, 89, 89); margin: 0px; padding: 0px; background: none 0% 0% / auto repeat scroll padding-box border-box rgba(0, 0, 0, 0);\">}</span></span></pre></div></div></div><ul data-lake-id=\"a6c67ee805f42cb011f5ec3569558c00\" lake-indent=\"0\" style=\"list-style-type: disc; margin: 0px; padding-left: 23px; font-size: 14px; color: rgb(38, 38, 38); line-height: 1.74; letter-spacing: 0.05em; outline-style: none; overflow-wrap: break-word;\"><li data-lake-id=\"57a2a98a919f4c0b20d747c0dafc9206\">结果: &lt;green&gt;测试成功&lt;/green&gt;<br></li></ul><p data-lake-id=\"04c409bd16cb6cfca67f5e71d4d04b74\" style=\"font-size: 14px; color: rgb(38, 38, 38); line-height: 1.74; letter-spacing: 0.05em; outline-style: none; overflow-wrap: break-word; margin: 0px;\"><br></p><h4 data-lake-id=\"6aa7654eb495222ea447a0d106226fd6\" id=\"zXYnB\" style=\"padding: 7px 0px; margin: 0px; font-weight: 700; font-size: 16px; line-height: 24px;\">折叠框</h4><ul data-lake-id=\"dd3b78297e0370f77495ddff98b9cca5\" lake-indent=\"0\" style=\"list-style-type: disc; margin: 0px; padding-left: 23px; font-size: 14px; color: rgb(38, 38, 38); line-height: 1.74; letter-spacing: 0.05em; outline-style: none; overflow-wrap: break-word;\"><li data-lake-id=\"f4b04702b80f9816dffa81cb9887e09f\">结果: &lt;red&gt;测试失败&lt;/red&gt; , 腾讯云函数无法激活GitHub Actions</li></ul></div>",
    "body_lake": "<!doctype lake><meta name=\"doc-version\" content=\"1\" /><meta name=\"viewport\" content=\"fixed\" /><meta name=\"typography\" content=\"classic\" /><p data-lake-id=\"f65514329048c34b89eac82f1e24f85b\"><br /></p><p data-lake-id=\"116ddff8e632eba8724aac7994875690\">date: &quot;2020-3-30 00:00:00&quot;</p><p data-lake-id=\"f0b7e771763a9bb17f9655cd1b8f4cda\">body: [article, comments]</p><p data-lake-id=\"37e8cbef3d702a9a483aebcd0bd7a27d\">cover: false</p><p data-lake-id=\"9a4fdff11b4fa5d67f7f154b18a6b72f\">valine:</p><p data-lake-id=\"1f4a705485a45919fc0925aef6cdb697\"> placeholder: 有什么感想? 发射犇犇</p><p data-lake-id=\"0564e95a046d27843f61ac9099628e4f\">mathjax: true</p><p data-lake-id=\"09841c28b00c7a7d569b52cb59f76cbe\">tags:</p><p data-lake-id=\"95d5ba826c80dd2339c6bfe124282e66\">- test</p><p data-lake-id=\"95243f401ea3360e90aea7111da99935\">categories:</p><p data-lake-id=\"ec627cd9ba6f4469b174cb983be99320\">- [Dev, hexo]</p><p data-lake-id=\"df44182a667e6aeec7cf972d37754739\"><br /></p><p data-lake-id=\"d0f25603b0b8a1f76e91065a38b40407\"><span style=\"color: #6A737D;\">---</span></p><blockquote><p data-lake-id=\"90254a0cf09df4e794183f3fd8f8bc8d\">这篇文章来自于云端的语雀</p></blockquote><p data-lake-id=\"1614ef987dbe837b7a28bc67218ad48a\">&lt;!--more--&gt;</p><h2 data-lake-id=\"333084cbba87814bcde072999a188966\" id=\"trTVW\">语雀云端编辑Hexo文章</h2><blockquote><p data-lake-id=\"76092aee7111b8b9f517aa005642ba69\">让你的 <a href=\"https://hexo.io\" target=\"_blank\">Hexo</a> 静态博客实现与 <a href=\"https://wordpress.org\" target=\"_blank\">Wordpress</a> 一样丝滑的文章发布体验</p><p data-lake-id=\"330288d10127f7cdbec9e0004f2853bf\">参见 https://zhwei.cn/hexo-github-actions-yuque/ \n<br /></p></blockquote><h2 data-lake-id=\"b6ad50776958d4df6750a5a02ff64a89\" id=\"nFaOR\">复杂格式测试</h2><h4 data-lake-id=\"0b3e57f310b7c059be9c73c5fa0cbda8\" id=\"ih913\">Container</h4><ul data-lake-id=\"6e16d3cebe901eae886c0c2976dbb6e1\"><li data-lake-id=\"814a6732be5815f744ca2e3eec86ac78\">结果: &lt;red&gt;测试失败&lt;/red&gt; , 腾讯云函数无法激活GitHub Actions</li></ul><h4 data-lake-id=\"3efde790e31791d18cd181be40b10be1\" id=\"MKVQi\">Code Block</h4><p data-lake-id=\"16344c0ab8d8c2b3a6970ea796962918\"><br /></p><card type=\"block\" name=\"codeblock\" value=\"data:%7B%22mode%22%3A%22cpp%22%2C%22code%22%3A%22%23include%20%3Ccstdio%3E%5Cn%5Cnint%20main()%5Cn%7B%5Cn%20%20%20%20puts(%5C%22U%20AK%20IOI!%5C%22)%3B%5Cn%20%20%20%20return%20main()%3B%5Cn%7D%22%2C%22id%22%3A%222GlFT%22%7D\"></card><ul data-lake-id=\"a6c67ee805f42cb011f5ec3569558c00\"><li data-lake-id=\"57a2a98a919f4c0b20d747c0dafc9206\">结果: &lt;green&gt;测试成功&lt;/green&gt;<br /></li></ul><p data-lake-id=\"04c409bd16cb6cfca67f5e71d4d04b74\"><br /></p><h4 data-lake-id=\"6aa7654eb495222ea447a0d106226fd6\" id=\"zXYnB\">折叠框</h4><ul data-lake-id=\"dd3b78297e0370f77495ddff98b9cca5\"><li data-lake-id=\"f4b04702b80f9816dffa81cb9887e09f\">结果: &lt;red&gt;测试失败&lt;/red&gt; , 腾讯云函数无法激活GitHub Actions</li></ul>",
    "body_draft_lake": "<!doctype lake><meta name=\"doc-version\" content=\"1\" /><meta name=\"viewport\" content=\"fixed\" /><meta name=\"typography\" content=\"classic\" /><p data-lake-id=\"f65514329048c34b89eac82f1e24f85b\"><br /></p><p data-lake-id=\"116ddff8e632eba8724aac7994875690\">date: &quot;2020-3-30 00:00:00&quot;</p><p data-lake-id=\"f0b7e771763a9bb17f9655cd1b8f4cda\">body: [article, comments]</p><p data-lake-id=\"37e8cbef3d702a9a483aebcd0bd7a27d\">cover: false</p><p data-lake-id=\"9a4fdff11b4fa5d67f7f154b18a6b72f\">valine:</p><p data-lake-id=\"1f4a705485a45919fc0925aef6cdb697\"> placeholder: 有什么感想? 发射犇犇</p><p data-lake-id=\"0564e95a046d27843f61ac9099628e4f\">mathjax: true</p><p data-lake-id=\"09841c28b00c7a7d569b52cb59f76cbe\">tags:</p><p data-lake-id=\"95d5ba826c80dd2339c6bfe124282e66\">- test</p><p data-lake-id=\"95243f401ea3360e90aea7111da99935\">categories:</p><p data-lake-id=\"ec627cd9ba6f4469b174cb983be99320\">- [Dev, hexo]</p><p data-lake-id=\"df44182a667e6aeec7cf972d37754739\"><br /></p><p data-lake-id=\"d0f25603b0b8a1f76e91065a38b40407\"><span style=\"color: #6A737D;\">---</span></p><blockquote><p data-lake-id=\"90254a0cf09df4e794183f3fd8f8bc8d\">这篇文章来自于云端的语雀</p></blockquote><p data-lake-id=\"1614ef987dbe837b7a28bc67218ad48a\">&lt;!--more--&gt;</p><h2 data-lake-id=\"333084cbba87814bcde072999a188966\" id=\"trTVW\">语雀云端编辑Hexo文章</h2><blockquote><p data-lake-id=\"76092aee7111b8b9f517aa005642ba69\">让你的 <a href=\"https://hexo.io\" target=\"_blank\">Hexo</a> 静态博客实现与 <a href=\"https://wordpress.org\" target=\"_blank\">Wordpress</a> 一样丝滑的文章发布体验</p><p data-lake-id=\"330288d10127f7cdbec9e0004f2853bf\">参见 https://zhwei.cn/hexo-github-actions-yuque/ \n<br /></p></blockquote><h2 data-lake-id=\"b6ad50776958d4df6750a5a02ff64a89\" id=\"nFaOR\">复杂格式测试</h2><h4 data-lake-id=\"0b3e57f310b7c059be9c73c5fa0cbda8\" id=\"ih913\">Container</h4><ul data-lake-id=\"6e16d3cebe901eae886c0c2976dbb6e1\"><li data-lake-id=\"814a6732be5815f744ca2e3eec86ac78\">结果: &lt;red&gt;测试失败&lt;/red&gt; , 腾讯云函数无法激活GitHub Actions</li></ul><h4 data-lake-id=\"3efde790e31791d18cd181be40b10be1\" id=\"MKVQi\">Code Block</h4><p data-lake-id=\"16344c0ab8d8c2b3a6970ea796962918\"><br /></p><card type=\"block\" name=\"codeblock\" value=\"data:%7B%22mode%22%3A%22cpp%22%2C%22code%22%3A%22%23include%20%3Ccstdio%3E%5Cn%5Cnint%20main()%5Cn%7B%5Cn%20%20%20%20puts(%5C%22U%20AK%20IOI!%5C%22)%3B%5Cn%20%20%20%20return%20main()%3B%5Cn%7D%22%2C%22id%22%3A%222GlFT%22%7D\"></card><ul data-lake-id=\"a6c67ee805f42cb011f5ec3569558c00\"><li data-lake-id=\"57a2a98a919f4c0b20d747c0dafc9206\">结果: &lt;green&gt;测试成功&lt;/green&gt;<br /></li></ul><p data-lake-id=\"04c409bd16cb6cfca67f5e71d4d04b74\"><br /></p><h4 data-lake-id=\"6aa7654eb495222ea447a0d106226fd6\" id=\"zXYnB\">折叠框</h4><ul data-lake-id=\"dd3b78297e0370f77495ddff98b9cca5\"><li data-lake-id=\"f4b04702b80f9816dffa81cb9887e09f\">结果: &lt;red&gt;测试失败&lt;/red&gt; , 腾讯云函数无法激活GitHub Actions</li></ul>",
    "public": 1,
    "status": 1,
    "view_status": 0,
    "read_status": 1,
    "likes_count": 0,
    "comments_count": 0,
    "content_updated_at": "2020-03-30T23:53:24.000Z",
    "deleted_at": null,
    "created_at": "2020-03-29T14:37:08.000Z",
    "updated_at": "2020-03-30T23:54:14.000Z",
    "published_at": "2020-03-30T23:54:13.000Z",
    "first_published_at": "2020-03-29T14:40:17.000Z",
    "word_count": 162,
    "cover": null,
    "description": "date: \"2020-3-30 00:00:00\"body: [article, comments]cover: falsevaline: placeholder: 有什么感想? 发射犇犇mathjax: truetags:- testcategories:- [Dev, hexo]---这...",
    "custom_description": null,
    "_serializer": "v2.doc_detail"
  }
]