{"per_page":10,"total":1,"current":1,"data":[{"title":"【Solution】ABC 246 Ex. 01? Queries","date":"2022-04-07T00:00:00.000Z","date_formatted":{"ll":"Apr 7, 2022","L":"04/07/2022","MM-DD":"04-07"},"link":"solution-abc246-ex"},{"title":"【Solution】[NOI Online 2 提高组]子序列问题-线段树","date":"2022-03-01T00:00:00.000Z","date_formatted":{"ll":"Mar 1, 2022","L":"03/01/2022","MM-DD":"03-01"},"link":"solution-luogu-6477"},{"title":"【Algorithm Notes】线段树的一些技巧","date":"2020-11-07T00:00:00.000Z","date_formatted":{"ll":"Nov 7, 2020","L":"11/07/2020","MM-DD":"11-07"},"link":"segment-tree-tricks"}],"name":"线段树"}